aws_cost_optimization/__init__.py
aws_cost_optimization/_cloudwatch_costing.py
aws_cost_optimization/_ec2_costing.py
aws_cost_optimization/_elb_costing.py
aws_cost_optimization/_kms_costing.py
aws_cost_optimization/_rds_costing.py
aws_cost_optimization/_ri_recommendations.py
aws_cost_optimization/_savings_plan.py
aws_cost_optimization/utils.py
aws_cost_optimization-0.5.0.dist-info/LICENCE
aws_cost_optimization-0.5.0.dist-info/METADATA
aws_cost_optimization-0.5.0.dist-info/WHEEL
aws_cost_optimization-0.5.0.dist-info/top_level.txt
aws_cost_optimization-0.5.0.dist-info/RECORD
