Metadata-Version: 2.1
Name: aws_cost_optimization
Version: 0.5.0
Summary: Provides AWS cost recommendations
Author-email: "dheeraj.banodha" <dheeraj.banodha@impetus.com>
Classifier: Programming Language :: Python :: 3
Classifier: Operating System :: OS Independent
Requires-Python: >=3.8
License-File: LICENCE
Requires-Dist: boto3
Requires-Dist: pytz
